pynetkit/__init__.py
pynetkit/cli/__init__.py
pynetkit/cli/__main__.py
pynetkit/cli/cli_curses.py
pynetkit/cli/cli_simple.py
pynetkit/cli/command.py
pynetkit/cli/commands/base.py
pynetkit/cli/commands/config.py
pynetkit/cli/commands/exit.py
pynetkit/cli/commands/help.py
pynetkit/cli/commands/modules/dhcp.py
pynetkit/cli/commands/modules/dns.py
pynetkit/cli/commands/modules/network.py
pynetkit/cli/commands/modules/ntp.py
pynetkit/cli/commands/modules/proxy.py
pynetkit/cli/commands/modules/wifi.py
pynetkit/cli/config.py
pynetkit/cli/eventlog.py
pynetkit/cli/util/mce.py
pynetkit/cli/windows/__init__.py
pynetkit/cli/windows/base.py
pynetkit/cli/windows/input.py
pynetkit/cli/windows/input_keycodes.py
pynetkit/cli/windows/log.py
pynetkit/modules/base/__init__.py
pynetkit/modules/base/base.py
pynetkit/modules/base/event.py
pynetkit/modules/base/future.py
pynetkit/modules/base/logger.py
pynetkit/modules/base/model.py
pynetkit/modules/base/utils.py
pynetkit/modules/dhcp/__init__.py
pynetkit/modules/dhcp/enums.py
pynetkit/modules/dhcp/events.py
pynetkit/modules/dhcp/module.py
pynetkit/modules/dhcp/structs.py
pynetkit/modules/dns/__init__.py
pynetkit/modules/dns/events.py
pynetkit/modules/dns/module.py
pynetkit/modules/http/__init__.py
pynetkit/modules/http/decorator.py
pynetkit/modules/http/events.py
pynetkit/modules/http/module.py
pynetkit/modules/http/types.py
pynetkit/modules/mqtt/__init__.py
pynetkit/modules/mqtt/decorator.py
pynetkit/modules/mqtt/events.py
pynetkit/modules/mqtt/module.py
pynetkit/modules/mqtt/types.py
pynetkit/modules/network/__init__.py
pynetkit/modules/network/common.py
pynetkit/modules/network/linux.py
pynetkit/modules/network/module.py
pynetkit/modules/network/windows.py
pynetkit/modules/ntp/__init__.py
pynetkit/modules/ntp/events.py
pynetkit/modules/ntp/module.py
pynetkit/modules/ntp/structs.py
pynetkit/modules/proxy/__init__.py
pynetkit/modules/proxy/events.py
pynetkit/modules/proxy/module.py
pynetkit/modules/proxy/structs.py
pynetkit-1.4.0.dist-info/METADATA
pynetkit-1.4.0.dist-info/WHEEL
pynetkit-1.4.0.dist-info/entry_points.txt
pynetkit-1.4.0.dist-info/RECORD
