Metadata-Version: 2.3
Name: pynetkit
Version: 1.4.0
Summary: Reverse engineering utilities for several popular network protocols
License: MIT
Author: Kuba Szczodrzyński
Author-email: kuba@szczodrzynski.pl
Requires-Python: >=3.10,<4.0
Classifier: License :: OSI Approved :: MIT License
Classifier: Programming Language :: Python :: 3
Classifier: Programming Language :: Python :: 3.10
Classifier: Programming Language :: Python :: 3.11
Classifier: Programming Language :: Python :: 3.12
Classifier: Programming Language :: Python :: 3.13
Requires-Dist: amqtt (==0.11.0b1)
Requires-Dist: bitstruct (>=8.20.0,<9.0.0)
Requires-Dist: click (>=8.1.7,<9.0.0)
Requires-Dist: cloup (>=3.0.5,<4.0.0)
Requires-Dist: colorama (>=0.4.6,<0.5.0)
Requires-Dist: dnslib (>=0.9.25,<0.10.0)
Requires-Dist: icmplib (>=3.0.4,<4.0.0)
Requires-Dist: ifaddr (>=0.2.0,<0.3.0)
Requires-Dist: importlib-metadata
Requires-Dist: macaddress (>=2.0.2,<3.0.0)
Requires-Dist: prettytable (>=3.12.0,<4.0.0)
Requires-Dist: py-datastruct (>=1.1.0,<2.0.0)
Requires-Dist: pycryptodome (>=3.21.0,<4.0.0)
Requires-Dist: pytimeparse (>=1.1.8,<2.0.0)
Requires-Dist: pywin32 ; sys_platform == "win32"
Requires-Dist: sslpsk3 (>=1.1.1,<2.0.0)
Requires-Dist: win32wifi (>=0.1.0,<0.2.0) ; sys_platform == "win32"
Requires-Dist: windows-curses (>=2.3.3,<3.0.0) ; sys_platform == "win32"
Requires-Dist: xmltodict (>=0.13.0,<0.14.0)
